pyzefir/__init__.py
pyzefir/cli/__init__.py
pyzefir/cli/__main__.py
pyzefir/cli/logger.py
pyzefir/cli/runner.py
pyzefir/graph/__init__.py
pyzefir/graph/constants.py
pyzefir/graph/network_diagram.py
pyzefir/graph/utils.py
pyzefir/model/__init__.py
pyzefir/model/exception_formatter.py
pyzefir/model/exceptions.py
pyzefir/model/network.py
pyzefir/model/network_element.py
pyzefir/model/network_validator.py
pyzefir/model/utils.py
pyzefir/model/network_aggregator/__init__.py
pyzefir/model/network_aggregator/aggregation_schemas.py
pyzefir/model/network_aggregator/network_aggregator.py
pyzefir/model/network_aggregator/utils.py
pyzefir/model/network_elements/__init__.py
pyzefir/model/network_elements/aggregated_consumer.py
pyzefir/model/network_elements/bus.py
pyzefir/model/network_elements/capacity_bound.py
pyzefir/model/network_elements/capacity_factor.py
pyzefir/model/network_elements/demand_chunk.py
pyzefir/model/network_elements/demand_profile.py
pyzefir/model/network_elements/dsr.py
pyzefir/model/network_elements/emission_fee.py
pyzefir/model/network_elements/fuel.py
pyzefir/model/network_elements/generation_fraction.py
pyzefir/model/network_elements/line.py
pyzefir/model/network_elements/local_balancing_stack.py
pyzefir/model/network_elements/transmission_fee.py
pyzefir/model/network_elements/energy_source_types/__init__.py
pyzefir/model/network_elements/energy_source_types/energy_source_type_base.py
pyzefir/model/network_elements/energy_source_types/generator_type.py
pyzefir/model/network_elements/energy_source_types/storage_type.py
pyzefir/model/network_elements/energy_sources/__init__.py
pyzefir/model/network_elements/energy_sources/energy_source_base.py
pyzefir/model/network_elements/energy_sources/generator.py
pyzefir/model/network_elements/energy_sources/storage.py
pyzefir/optimization/__init__.py
pyzefir/optimization/exportable_results.py
pyzefir/optimization/input_data.py
pyzefir/optimization/model.py
pyzefir/optimization/opt_config.py
pyzefir-0.5.0.dist-info/LICENSE.txt
pyzefir-0.5.0.dist-info/METADATA
pyzefir-0.5.0.dist-info/WHEEL
pyzefir-0.5.0.dist-info/entry_points.txt
pyzefir-0.5.0.dist-info/top_level.txt
pyzefir-0.5.0.dist-info/RECORD
