Metadata-Version: 2.1
Name: pyzefir
Version: 0.5.0
Author-email: Narodowe Centrum Badań Jądrowych <office@idea.edu.pl>
License: The MIT License (MIT)
Classifier: Environment :: Console
Classifier: Intended Audience :: Science/Research
Classifier: License :: OSI Approved :: MIT License
Classifier: Natural Language :: English
Classifier: Operating System :: OS Independent
Classifier: Programming Language :: Python :: 3.11
Classifier: Topic :: Scientific/Engineering
License-File: LICENSE.txt
Requires-Dist: numpy~=1.24.2
Requires-Dist: pandas==2.0.1
Requires-Dist: networkx~=3.0
Requires-Dist: setuptools==67.8.0
Requires-Dist: matplotlib~=3.7.1
Requires-Dist: openpyxl==3.1.2
Requires-Dist: gurobipy~=11.0.2
Requires-Dist: bidict~=0.22.1
Requires-Dist: scipy~=1.11.1
Requires-Dist: click~=8.1.6
Requires-Dist: sanitize-filename~=1.2.0
Requires-Dist: XlsxWriter~=3.1.2
Requires-Dist: linopy==0.3.13
Requires-Dist: xarray~=2024.6.0
Requires-Dist: GitPython==3.1.43
Requires-Dist: pyarrow==17.0.0
Provides-Extra: dev
Requires-Dist: flake8==7.0.0; extra == "dev"
Requires-Dist: black==24.2.0; extra == "dev"
Requires-Dist: pre-commit; extra == "dev"
Requires-Dist: pytest==7.4.4; extra == "dev"
Requires-Dist: pytest-cov~=4.0.0; extra == "dev"
Requires-Dist: pytest-mock~=3.11.1; extra == "dev"
Requires-Dist: pytest-lazy-fixture~=0.6.3; extra == "dev"
Requires-Dist: pytest-xdist~=3.5.0; extra == "dev"
Requires-Dist: pylama[mypy,radon,toml]; extra == "dev"
Requires-Dist: tox; extra == "dev"
Requires-Dist: sphinx; extra == "dev"
Provides-Extra: gurobi
Requires-Dist: gurobipy~=11.0.2; extra == "gurobi"
Provides-Extra: highs
Requires-Dist: highspy~=1.5.3; extra == "highs"
